fc_xy_bigdata.py
fc_wxy-2.1.0.dist-info/METADATA
fc_wxy-2.1.0.dist-info/WHEEL
fc_wxy-2.1.0.dist-info/top_level.txt
fc_wxy-2.1.0.dist-info/RECORD
