Metadata-Version: 2.1
Name: fc-wxy
Version: 2.1.0
Summary: 这是一个包
Home-page: UNKNOWN
Author: 大数据1
Author-email: 2698571909@qq.com
License: UNKNOWN
Platform: UNKNOWN
